rom/rom.v
module rom(
     input wire [2:0] addr,
     output wire [7:0] data   
); 

    assign data = (addr == 3'b000) ? 8'b00110011 :  // Define data for each memory location
                 (addr == 3'b001) ? 8'b11001100 :
                 (addr == 3'b010) ? 8'b01010101 :
                 (addr == 3'b011) ? 8'b10101010 :
                 (addr == 3'b100) ? 8'b11110000 :
                 (addr == 3'b101) ? 8'b00001111 :
                 (addr == 3'b110) ? 8'b10000001 :
                 (addr == 3'b111) ? 8'b01111110 : 8'b00000000;  // Default value for invalid addresses
endmodule

rom/rom_tb.v
module rom_tb;
    reg [2:0] address;
    wire [7:0] data;

    rom uut ( .addr(address), .data(data) );


    initial begin
        $monitor("Time = %0t, address = %0b, data = %0b", $time, address, data);
        address = 3'b000;
        #10;

        address = 3'b001;
        #10;

        address = 3'b010;
        #10;

        address = 3'b011;
        #10;

        address = 3'b100;
        #10;

        address = 3'b101;
        #10;

        address = 3'b110;
        #10;

        address = 3'b111;
        #10;
        $finish;

    end

    initial begin
       
        $dumpfile("rom.vcd");
        $dumpvars(0, rom_tb);
    end

endmodule //rom_tb

rom/rom.vcd
$date
	Sun Sep 29 13:38:32 2024
$end
$version
	Icarus Verilog
$end
$timescale
	1s
$end
$scope module rom_tb $end
$var wire 8 ! data [7:0] $end
$var reg 3 " address [2:0] $end
$scope module uut $end
$var wire 3 # addr [2:0] $end
$var wire 8 $ data [7:0] $end
$upscope $end
$upscope $end
$enddefinitions $end
#0
$dumpvars
b110011 $
b0 #
b0 "
b110011 !
$end
#10
b11001100 !
b11001100 $
b1 "
b1 #
#20
b1010101 !
b1010101 $
b10 "
b10 #
#30
b10101010 !
b10101010 $
b11 "
b11 #
#40
b11110000 !
b11110000 $
b100 "
b100 #
#50
b1111 !
b1111 $
b101 "
b101 #
#60
b10000001 !
b10000001 $
b110 "
b110 #
#70
b1111110 !
b1111110 $
b111 "
b111 #
