elevator_controller/elevator_controller.v
module elevator_controller (
    input clk, rst,
    input [4:0] floor_req,
    output reg [4:0] floor_pos
);
    parameter idle = 3'b000;
    parameter movingUP = 3'b001;
    parameter movingDOWN = 3'b010;
    parameter STOP = 3'b011;

    reg [2:0] state;
    reg [4:0] floor_pos_reg, floor_req_reg;

    always @(posedge clk) begin
        if(rst) begin
            state <= idle;
            floor_pos_reg <= 5'b00000;
            floor_req_reg <= 5'b00000;
        end else begin
            case (state)
                idle: begin
                    if(floor_req > floor_pos_reg) begin
                        state <= movingUP;
                    end else if(floor_req < floor_pos_reg) begin
                        state <= movingDOWN;
                    end else begin
                        state <= STOP;
                    end
                end 
                movingUP: begin
                    if(floor_req == floor_pos_reg) begin
                        state <= STOP;
                    end else begin
                        floor_pos_reg <= floor_pos_reg + 1;
                    end
                end
                movingDOWN: begin
                     if(floor_req == floor_pos_reg) begin
                        state <= STOP;
                    end else begin
                        floor_pos_reg <= floor_pos_reg - 1;
                    end
                end
                STOP: begin
                    floor_req_reg[floor_pos_reg] <= 1'b0; //clear request for current floor
                    if(floor_req_reg != 5'b00000) begin
                        if(floor_req > floor_pos_reg) begin
                            state <= movingUP;
                        end else if(floor_req < floor_pos_reg) begin
                            state <= movingDOWN;
                        end else begin
                            state <= STOP;
                        end
                    end else begin
                        state <= idle;
                    end
                end
                default: ;
            endcase
            floor_pos <= floor_pos_reg;
            floor_req_reg[floor_req] <= 1'b1; //set request for <this> floor
        end
    end    
endmodule

elevator_controller/elevator_controller_tb.v
module elevator_controller_tb;
    reg clk;
    reg rst;
    reg [4:0] floor_req;
    wire [4:0] floor_pos;

    elevator_controller uut (
        .clk(clk),
        .rst(rst),
        .floor_req(floor_req),
        .floor_pos(floor_pos)
    );
    always #5 clk = ~clk;
initial begin
        $dumpfile("elevator.vcd");
        $dumpvars(0, elevator_controller_tb);

        clk = 1'b0;
        rst = 1'b1;
        floor_req = 5'b00000;
        #10 rst = 1'b0; 
        #10 floor_req = 5'b00100; // request floor 3
        #100 floor_req = 5'b00010; // request floor 2
        #100 floor_req = 5'b01000; // request floor 4
        #100 floor_req = 5'b00001; // request floor 1
        #100 floor_req = 5'b11010; // request floor 5
        #1000;
        $finish; 
end
endmodule

elevator_controller/elevator.vcd
$date
	Thu Oct  3 23:54:21 2024
$end
$version
	Icarus Verilog
$end
$timescale
	1s
$end
$scope module elevator_controller_tb $end
$var wire 5 ! floor_pos [4:0] $end
$var reg 1 " clk $end
$var reg 5 # floor_req [4:0] $end
$var reg 1 $ rst $end
$scope module uut $end
$var wire 1 " clk $end
$var wire 5 % floor_req [4:0] $end
$var wire 1 $ rst $end
$var reg 5 & floor_pos [4:0] $end
$var reg 5 ' floor_pos_reg [4:0] $end
$var reg 5 ( floor_req_reg [4:0] $end
$var reg 3 ) state [2:0] $end
$upscope $end
$upscope $end
$enddefinitions $end
#0
$dumpvars
bx )
bx (
bx '
bx &
b0 %
1$
b0 #
0"
bx !
$end
#5
b0 (
b0 '
b0 )
1"
#10
0"
0$
#15
b1 (
b0 !
b0 &
b11 )
1"
#20
0"
b100 #
b100 %
#25
b1 )
b10000 (
1"
#30
0"
#35
b1 '
1"
#40
0"
#45
b1 !
b1 &
b10 '
1"
#50
0"
#55
b10 !
b10 &
b11 '
1"
#60
0"
#65
b11 !
b11 &
b100 '
1"
#70
0"
#75
b100 !
b100 &
b11 )
1"
#80
0"
#85
b10000 (
1"
#90
0"
#95
b10000 (
1"
#100
0"
#105
b10000 (
1"
#110
0"
#115
b10000 (
1"
#120
0"
b10 #
b10 %
#125
b10 )
b100 (
1"
#130
0"
#135
b11 '
1"
#140
0"
#145
b11 !
b11 &
b10 '
1"
#150
0"
#155
b10 !
b10 &
b11 )
1"
#160
0"
#165
b100 (
1"
#170
0"
#175
b100 (
1"
#180
0"
#185
b100 (
1"
#190
0"
#195
b100 (
1"
#200
0"
#205
b100 (
1"
#210
0"
#215
b100 (
1"
#220
0"
b1000 #
b1000 %
#225
b1 )
b0 (
1"
#230
0"
#235
b11 '
1"
#240
0"
#245
b11 !
b11 &
b100 '
1"
#250
0"
#255
b100 !
b100 &
b101 '
1"
#260
0"
#265
b101 !
b101 &
b110 '
1"
#270
0"
#275
b110 !
b110 &
b111 '
1"
#280
0"
#285
b111 !
b111 &
b1000 '
1"
#290
0"
#295
b1000 !
b1000 &
b11 )
1"
#300
0"
#305
b0 )
1"
#310
0"
#315
b11 )
1"
#320
0"
b1 #
b1 %
#325
b10 (
b0 )
1"
#330
0"
#335
b10 )
1"
#340
0"
#345
b111 '
1"
#350
0"
#355
b111 !
b111 &
b110 '
1"
#360
0"
#365
b110 !
b110 &
b101 '
1"
#370
0"
#375
b101 !
b101 &
b100 '
1"
#380
0"
#385
b100 !
b100 &
b11 '
1"
#390
0"
#395
b11 !
b11 &
b10 '
1"
#400
0"
#405
b10 !
b10 &
b1 '
1"
#410
0"
#415
b1 !
b1 &
b11 )
1"
#420
0"
b11010 #
b11010 %
#425
b1 )
b0 (
1"
#430
0"
#435
b10 '
1"
#440
0"
#445
b10 !
b10 &
b11 '
1"
#450
0"
#455
b11 !
b11 &
b100 '
1"
#460
0"
#465
b100 !
b100 &
b101 '
1"
#470
0"
#475
b101 !
b101 &
b110 '
1"
#480
0"
#485
b110 !
b110 &
b111 '
1"
#490
0"
#495
b111 !
b111 &
b1000 '
1"
#500
0"
#505
b1000 !
b1000 &
b1001 '
1"
#510
0"
#515
b1001 !
b1001 &
b1010 '
1"
#520
0"
#525
b1010 !
b1010 &
b1011 '
1"
#530
0"
#535
b1011 !
b1011 &
b1100 '
1"
#540
0"
#545
b1100 !
b1100 &
b1101 '
1"
#550
0"
#555
b1101 !
b1101 &
b1110 '
1"
#560
0"
#565
b1110 !
b1110 &
b1111 '
1"
#570
0"
#575
b1111 !
b1111 &
b10000 '
1"
#580
0"
#585
b10000 !
b10000 &
b10001 '
1"
#590
0"
#595
b10001 !
b10001 &
b10010 '
1"
#600
0"
#605
b10010 !
b10010 &
b10011 '
1"
#610
0"
#615
b10011 !
b10011 &
b10100 '
1"
#620
0"
#625
b10100 !
b10100 &
b10101 '
1"
#630
0"
#635
b10101 !
b10101 &
b10110 '
1"
#640
0"
#645
b10110 !
b10110 &
b10111 '
1"
#650
0"
#655
b10111 !
b10111 &
b11000 '
1"
#660
0"
#665
b11000 !
b11000 &
b11001 '
1"
#670
0"
#675
b11001 !
b11001 &
b11010 '
1"
#680
0"
#685
b11010 !
b11010 &
b11 )
1"
#690
0"
#695
b0 )
1"
#700
0"
#705
b11 )
1"
#710
0"
#715
b0 )
1"
#720
0"
#725
b11 )
1"
#730
0"
#735
b0 )
1"
#740
0"
#745
b11 )
1"
#750
0"
#755
b0 )
1"
#760
0"
#765
b11 )
1"
#770
0"
#775
b0 )
1"
#780
0"
#785
b11 )
1"
#790
0"
#795
b0 )
1"
#800
0"
#805
b11 )
1"
#810
0"
#815
b0 )
1"
#820
0"
#825
b11 )
1"
#830
0"
#835
b0 )
1"
#840
0"
#845
b11 )
1"
#850
0"
#855
b0 )
1"
#860
0"
#865
b11 )
1"
#870
0"
#875
b0 )
1"
#880
0"
#885
b11 )
1"
#890
0"
#895
b0 )
1"
#900
0"
#905
b11 )
1"
#910
0"
#915
b0 )
1"
#920
0"
#925
b11 )
1"
#930
0"
#935
b0 )
1"
#940
0"
#945
b11 )
1"
#950
0"
#955
b0 )
1"
#960
0"
#965
b11 )
1"
#970
0"
#975
b0 )
1"
#980
0"
#985
b11 )
1"
#990
0"
#995
b0 )
1"
#1000
0"
#1005
b11 )
1"
#1010
0"
#1015
b0 )
1"
#1020
0"
#1025
b11 )
1"
#1030
0"
#1035
b0 )
1"
#1040
0"
#1045
b11 )
1"
#1050
0"
#1055
b0 )
1"
#1060
0"
#1065
b11 )
1"
#1070
0"
#1075
b0 )
1"
#1080
0"
#1085
b11 )
1"
#1090
0"
#1095
b0 )
1"
#1100
0"
#1105
b11 )
1"
#1110
0"
#1115
b0 )
1"
#1120
0"
#1125
b11 )
1"
#1130
0"
#1135
b0 )
1"
#1140
0"
#1145
b11 )
1"
#1150
0"
#1155
b0 )
1"
#1160
0"
#1165
b11 )
1"
#1170
0"
#1175
b0 )
1"
#1180
0"
#1185
b11 )
1"
#1190
0"
#1195
b0 )
1"
#1200
0"
#1205
b11 )
1"
#1210
0"
#1215
b0 )
1"
#1220
0"
#1225
b11 )
1"
#1230
0"
#1235
b0 )
1"
#1240
0"
#1245
b11 )
1"
#1250
0"
#1255
b0 )
1"
#1260
0"
#1265
b11 )
1"
#1270
0"
#1275
b0 )
1"
#1280
0"
#1285
b11 )
1"
#1290
0"
#1295
b0 )
1"
#1300
0"
#1305
b11 )
1"
#1310
0"
#1315
b0 )
1"
#1320
0"
#1325
b11 )
1"
#1330
0"
#1335
b0 )
1"
#1340
0"
#1345
b11 )
1"
#1350
0"
#1355
b0 )
1"
#1360
0"
#1365
b11 )
1"
#1370
0"
#1375
b0 )
1"
#1380
0"
#1385
b11 )
1"
#1390
0"
#1395
b0 )
1"
#1400
0"
#1405
b11 )
1"
#1410
0"
#1415
b0 )
1"
