pseudorandomNumber/pseudorandomNumber.v
module pseudorandomNumber (
    input wire clk, rst,
    output wire [3:0] rand_out 
);

    reg [3:0] lfsr_state;  // 4-bit LFSR state register

    always @(posedge clk or posedge rst) begin
        if (rst) begin
            lfsr_state <= 4'b1001; // Initial state (can be any non-zero value)
        end else begin
      // XOR taps for a 4-bit LFSR: 4, 3
        lfsr_state <= {lfsr_state[2:0], lfsr_state[3] ^ lfsr_state[0]};
        end
    end

    assign rand_out = lfsr_state;

endmodule

pseudorandomNumber/pseudorandomNumber_tb.v
module pseudorandomNumber_tb;
    reg clk; 
    reg rst;
    wire [3:0] rand_out;

    pseudorandomNumber uut( .clk(clk), .rst(rst), .rand_out(rand_out) );

    always begin
        #5 clk = ~clk; 
    end

    initial begin

        $dumpfile("number.vcd");
        $dumpvars(0, pseudorandomNumber_tb);

        clk = 0;
        rst = 0;

        rst = 1;
        #10 rst = 0;

        $monitor("Time %t\t Output %b", $time, rand_out);

        #100; 
        $finish;
    end

endmodule

pseudorandomNumber/number.vcd
$date
	Thu Oct  3 21:26:45 2024
$end
$version
	Icarus Verilog
$end
$timescale
	1s
$end
$scope module pseudorandomNumber_tb $end
$var wire 4 ! rand_out [3:0] $end
$var reg 1 " clk $end
$var reg 1 # rst $end
$scope module uut $end
$var wire 1 " clk $end
$var wire 4 $ rand_out [3:0] $end
$var wire 1 # rst $end
$var reg 4 % lfsr_state [3:0] $end
$upscope $end
$upscope $end
$enddefinitions $end
#0
$dumpvars
b1001 %
b1001 $
1#
0"
b1001 !
$end
#5
1"
#10
0"
0#
#15
b10 !
b10 $
b10 %
1"
#20
0"
#25
b100 !
b100 $
b100 %
1"
#30
0"
#35
b1000 !
b1000 $
b1000 %
1"
#40
0"
#45
b1 !
b1 $
b1 %
1"
#50
0"
#55
b11 !
b11 $
b11 %
1"
#60
0"
#65
b111 !
b111 $
b111 %
1"
#70
0"
#75
b1111 !
b1111 $
b1111 %
1"
#80
0"
#85
b1110 !
b1110 $
b1110 %
1"
#90
0"
#95
b1101 !
b1101 $
b1101 %
1"
#100
0"
#105
b1010 !
b1010 $
b1010 %
1"
