flipflop/t/t_flipflop.v
module t_flipflop (
    input d, clk,
    output reg q
);
    always @(posedge clk) begin
        q = !d;
    end

endmodule

flipflop/t/t_flipflop_tb.v
module t_flipflop_tb;
    reg d, clk;
    wire q;

    // Instantiate the D flip-flop
    t_flipflop uut(
        .d(d),
        .clk(clk),
        .q(q)  // Connect the output q
    );

    // Clock generation
    initial begin
        clk = 0;
        forever #5 clk = ~clk;  // Toggle clock every 5 time units
    end

    // Stimulus process
    initial begin
        // Initialize inputs
        d = 0;

        // Apply test vectors
        #10 d = 1'b0;  // This will be captured on the next clock edge
        #10 d = 1'b1;  // This will be captured on the next clock edge
        #10 d = 1'b0;  // Another change for testing
        #10 d = 1'b1;  // Another change for testing

        // Wait some time and finish the simulation
        #50;
        $finish;
    end

    // Monitor signals
    initial begin
        $monitor("At time %0t: clk = %b, d = %b, q = %b", $time, clk, d, q);
    end

    // Dump waveform
    initial begin
        $dumpfile("tflipflop.vcd");
        $dumpvars(0, t_flipflop_tb);
    end
endmodule

flipflop/t/tflipflop.vcd
$date
	Wed Sep 25 15:57:34 2024
$end
$version
	Icarus Verilog
$end
$timescale
	1s
$end
$scope module t_flipflop_tb $end
$var wire 1 ! q $end
$var reg 1 " clk $end
$var reg 1 # d $end
$scope module uut $end
$var wire 1 " clk $end
$var wire 1 # d $end
$var reg 1 ! q $end
$upscope $end
$upscope $end
$enddefinitions $end
#0
$dumpvars
0#
0"
x!
$end
#5
1!
1"
#10
0"
#15
1"
#20
0"
1#
#25
0!
1"
#30
0"
0#
#35
1!
1"
#40
0"
1#
#45
0!
1"
