flipflop/jk/jk.v
module jk (
    input j, k, clk, reset,  
    output reg q             
);
    always @(posedge clk or posedge reset) begin
        if (reset) 
            q <= 1'b0;  
        else begin
            case ({j, k})
                2'b00 : q <= q;   // No change
                2'b01 : q <= 1'b0; // Reset output to 0
                2'b10 : q <= 1'b1; // Set output to 1
                2'b11 : q <= ~q;   // Toggle output
            endcase
        end
    end
endmodule

flipflop/jk/jk_tb.v
module jk_tb;
    reg j, k, clk, reset;
    wire q;

    // Instantiate the JK flip-flop
    jk uut (
        .j(j),
        .k(k),
        .clk(clk),
        .reset(reset),
        .q(q)
    );

    // Clock generation
    initial begin
        clk = 0;
        forever #5 clk = ~clk;  // Toggle clock every 5 time units
    end

    // Stimulus process
    initial begin
        // Initialize inputs
        j = 0; k = 0; reset = 1;  // Start with reset high
        #10 j = 1; k = 0;  // Set condition
        #10 j = 0; k = 1;  // Reset condition
        #10 j = 1; k = 1;  // Toggle condition
        #10 j = 0; k = 0;  // No change
        #10 reset = 0;  // Deassert reset after 10 time units
        
        // Apply test vectors
        #10 j = 1; k = 0;  // Set condition
        #10 j = 0; k = 1;  // Reset condition
        #10 j = 1; k = 1;  // Toggle condition
        #30 j = 0; k = 0;  // No change
        
        // Finish simulation
        #50;
        $finish;
    end

    // Monitor signals
    initial begin
        $monitor("At time %0t: clk = %b, j = %b, k = %b, reset = %b, q = %b", 
                 $time, clk, j, k, reset, q);
    end

    // Dump waveform
    initial begin
        $dumpfile("jk.vcd");
        $dumpvars(0, jk_tb);
    end
endmodule

flipflop/jk/jk.vcd
$date
	Wed Sep 25 17:25:33 2024
$end
$version
	Icarus Verilog
$end
$timescale
	1s
$end
$scope module jk_tb $end
$var wire 1 ! q $end
$var reg 1 " clk $end
$var reg 1 # j $end
$var reg 1 $ k $end
$var reg 1 % reset $end
$scope module uut $end
$var wire 1 " clk $end
$var wire 1 # j $end
$var wire 1 $ k $end
$var wire 1 % reset $end
$var reg 1 ! q $end
$upscope $end
$upscope $end
$enddefinitions $end
#0
$dumpvars
1%
0$
0#
0"
0!
$end
#5
1"
#10
0"
1#
#15
1"
#20
0"
1$
0#
#25
1"
#30
0"
1#
#35
1"
#40
0"
0$
0#
#45
1"
#50
0"
0%
#55
1"
#60
0"
1#
#65
1!
1"
#70
0"
1$
0#
#75
0!
1"
#80
0"
1#
#85
1!
1"
#90
0"
#95
0!
1"
#100
0"
#105
1!
1"
#110
0"
0$
0#
