sequence_detector/moore/moore.v
module moore ( // 1101 sequence detector
    input x, clk, rst,
    output reg y,
    output [2:0] state // Use wire to monitor state
);
    reg [2:0] ps, ns;
    localparam sin = 3'd0, s1 = 3'd1, s11 = 3'd2, s110 = 3'd3, s1101 = 3'd4;

    // State transition on the rising edge of the clock or reset
    always @(posedge clk or posedge rst) begin
        if (rst) begin
            ps <= sin; // Reset to initial state
        end else begin
            ps <= ns; // Transition to next state
        end
    end

    // Next state logic and output logic
    always @(*) begin
        // Default assignments to avoid latches
        ns = ps;
        y = 1'b0;

        case (ps)
            sin: begin
                ns = x ? s1 : sin;
            end 
            s1: begin
                ns = x ? s11 : sin;
            end
            s11: begin
                ns = x ? s1 : s110;
            end
            s110: begin
                ns = x ? s1101 : sin;
            end
            s1101: begin
                ns = x ? s11 : sin;
                y = 1'b1; // Detect sequence
            end
            default: begin
                ns = sin; // Safe fallback in case of unexpected state
            end
        endcase
    end

    // Output the current state as wire (ps)
    assign state = ps;

endmodule

sequence_detector/moore/moore_tb.v
module moore_tb;
    reg x, clk, rst;
    wire y;
    wire [2:0] state; // To monitor the state

    // Instantiate the Moore sequence detector
    moore uut(
        .x(x),
        .clk(clk),
        .rst(rst),
        .y(y),
        .state(state) // Connect state to monitor
    );

    // Clock generation
    initial begin
        clk = 0;
        forever #5 clk = ~clk; // 10 time units per cycle
    end

    // Test sequence
    initial begin
        $dumpfile("moore.vcd");
        $dumpvars(0, moore_tb);

        // Apply reset
        rst = 1;
        #10;
        rst = 0;

        // Input sequence for 1101
        x = 1; #10; // First 1
        x = 1; #10; // Second 1
        x = 0; #10; // First 0
        x = 1; #10; // Final 1 (should detect 1101)

        // Continue the simulation to observe more output
        x = 1; #10;
        x = 0; #10;
        x = 1; #10; // Should display 1 again.

        #100;
        $finish;
    end
endmodule

sequence_detector/moore/moore.vcd
$date
	Tue Oct  1 22:33:02 2024
$end
$version
	Icarus Verilog
$end
$timescale
	1s
$end
$scope module moore_tb $end
$var wire 1 ! y $end
$var wire 3 " state [2:0] $end
$var reg 1 # clk $end
$var reg 1 $ rst $end
$var reg 1 % x $end
$scope module uut $end
$var wire 1 # clk $end
$var wire 1 $ rst $end
$var wire 3 & state [2:0] $end
$var wire 1 % x $end
$var reg 3 ' ns [2:0] $end
$var reg 3 ( ps [2:0] $end
$var reg 1 ! y $end
$upscope $end
$upscope $end
$enddefinitions $end
#0
$dumpvars
b0 (
b0x '
b0 &
x%
1$
0#
b0 "
0!
$end
#5
1#
#10
b1 '
0#
1%
0$
#15
b10 '
b1 "
b1 &
b1 (
1#
#20
0#
#25
b1 '
b10 "
b10 &
b10 (
1#
#30
b11 '
0#
0%
#35
b0 '
b11 "
b11 &
b11 (
1#
#40
b100 '
0#
1%
#45
1!
b10 '
b100 "
b100 &
b100 (
1#
#50
0#
#55
b1 '
0!
b10 "
b10 &
b10 (
1#
#60
b11 '
0#
0%
#65
b0 '
b11 "
b11 &
b11 (
1#
#70
b100 '
0#
1%
#75
1!
b10 '
b100 "
b100 &
b100 (
1#
#80
0#
#85
b1 '
0!
b10 "
b10 &
b10 (
1#
#90
0#
#95
b10 '
b1 "
b1 &
b1 (
1#
#100
0#
#105
b1 '
b10 "
b10 &
b10 (
1#
#110
0#
#115
b10 '
b1 "
b1 &
b1 (
1#
#120
0#
#125
b1 '
b10 "
b10 &
b10 (
1#
#130
0#
#135
b10 '
b1 "
b1 &
b1 (
1#
#140
0#
#145
b1 '
b10 "
b10 &
b10 (
1#
#150
0#
#155
b10 '
b1 "
b1 &
b1 (
1#
#160
0#
#165
b1 '
b10 "
b10 &
b10 (
1#
#170
0#
#175
b10 '
b1 "
b1 &
b1 (
1#
