RoundRobin/round_robin_arbiter.v
module round_robin_arbiter (
    input clk, reset,
    input [3:0] request,
    output reg [3:0] grant
);
    // Define the states with proper 3-bit parameters (fix the size issue)
    parameter [2:0] idle = 3'd0;
    parameter [2:0] state_0 = 3'd1;
    parameter [2:0] state_1 = 3'd2;
    parameter [2:0] state_2 = 3'd3;
    parameter [2:0] state_3 = 3'd4;

    reg [2:0] current, next;

    // Sequential state transition block, updating current state on clock edge or reset
    always @(posedge clk or posedge reset) begin
        if(reset) begin
            current <= idle;
        end else begin
            current <= next;
        end
    end

    // Combinational logic for next state
    always @(*) begin
        case (current)
            idle: begin
                if(request[0]) begin
                    next = state_0;
                end else if(request[1]) begin
                    next = state_1;
                end else if(request[2]) begin
                    next = state_2;
                end else if(request[3]) begin
                    next = state_3;
                end else begin
                    next = idle;
                end          
            end

            state_0: begin 
               if(request[1]) begin
                    next = state_1;
                end else if(request[2]) begin
                    next = state_2;
                end else if(request[3]) begin
                    next = state_3;
                end else if(request[0]) begin
                    next = state_0;
                end else begin
                    next = idle;
                end       
            end

            state_1: begin
                if(request[2]) begin
                    next = state_2;
                end else if(request[3]) begin
                    next = state_3;
                end else if(request[0]) begin
                    next = state_0;
                end else if(request[1]) begin
                    next = state_1;
                end else begin
                    next = idle;
                end       
            end

            state_2: begin
                if(request[3]) begin
                    next = state_3;
                end else if(request[0]) begin
                    next = state_0;
                end else if(request[1]) begin
                    next = state_1;
                end else if(request[2]) begin
                    next = state_2;
                end else begin
                    next = idle;
                end       
            end

            state_3: begin
                if(request[0]) begin
                    next = state_0;
                end else if(request[1]) begin
                    next = state_1;
                end else if(request[2]) begin
                    next = state_2;
                end else if(request[3]) begin
                    next = state_3;
                end else begin
                    next = idle;
                end       
            end

            default: begin
                next = idle;
            end
        endcase
    end

    // Combinational logic for grant signals based on current state
    always @(*) begin
        case (current)
            state_0: grant = 4'h1;
            state_1: grant = 4'h2;
            state_2: grant = 4'h4;
            state_3: grant = 4'h8; 
            default: grant = 4'h0;
        endcase
    end

endmodule

RoundRobin/round_robin_arbiter_tb.v
module round_robin_arbiter_tb;
    reg clk, reset;
    reg [3:0] request;
    wire [3:0] grant;

    round_robin_arbiter uut(
        .clk(clk),
        .reset(reset),
        .request(request),
        .grant(grant)
    );

    // Clock generation
    always #5 clk = ~clk;

    // Display signals for debugging
    initial begin
        $monitor("Time: %0t | request: %b | grant: %b", $time, request, grant);
    end

    // Test stimulus
    initial begin
        $dumpfile("round_robin.vcd");
        $dumpvars(0, round_robin_arbiter_tb);

        clk = 0;
        reset = 1;
        request = 4'h0;

        #10 reset = 0;

        // Different request patterns
        request = 4'b1011;  // Time: 10
        #20;
        request = 4'b1111;  // Time: 30
        #20;
        request = 4'b1000;  // Time: 50
        #20;
        request = 4'b1001;  // Time: 70
        #20;
        request = 4'b1100;  // Time: 90
        #20;
        $finish;   
    end
endmodule

RoundRobin/round_robin.vcd
$date
	Wed Oct  2 23:54:19 2024
$end
$version
	Icarus Verilog
$end
$timescale
	1s
$end
$scope module round_robin_arbiter_tb $end
$var wire 4 ! grant [3:0] $end
$var reg 1 " clk $end
$var reg 4 # request [3:0] $end
$var reg 1 $ reset $end
$scope module uut $end
$var wire 1 " clk $end
$var wire 4 % request [3:0] $end
$var wire 1 $ reset $end
$var reg 3 & current [2:0] $end
$var reg 4 ' grant [3:0] $end
$var reg 3 ( next [2:0] $end
$upscope $end
$upscope $end
$enddefinitions $end
#0
$dumpvars
b0 (
b0 '
b0 &
b0 %
1$
b0 #
0"
b0 !
$end
#5
1"
#10
b1 (
0"
b1011 #
b1011 %
0$
#15
b1 !
b1 '
b10 (
b1 &
1"
#20
0"
#25
b10 !
b10 '
b100 (
b10 &
1"
#30
b11 (
0"
b1111 #
b1111 %
#35
b100 !
b100 '
b100 (
b11 &
1"
#40
0"
#45
b1000 !
b1000 '
b1 (
b100 &
1"
#50
b100 (
0"
b1000 #
b1000 %
#55
1"
#60
0"
#65
1"
#70
b1 (
0"
b1001 #
b1001 %
#75
b1 !
b1 '
b100 (
b1 &
1"
#80
0"
#85
b1000 !
b1000 '
b1 (
b100 &
1"
#90
b11 (
0"
b1100 #
b1100 %
#95
b100 !
b100 '
b100 (
b11 &
1"
#100
0"
#105
b1000 !
b1000 '
b11 (
b100 &
1"
