pwm/pwm.v
module pwm(
    input clk,
    output reg [3:0] out  // Use reg since we are updating this in always block
);

    reg [7:0] count = 0;

    always @(posedge clk) begin
        if (count < 99)
            count <= count + 1;
        else
            count <= 0;
    end

    // Generate PWM outputs with different duty cycles
    always @(posedge clk) begin
        out = 4'b0000;
        out[0] <= (count < 20) ? 1 : 0;  // 20% duty cycle
        out[1] <= (count < 40) ? 1 : 0;  // 40% duty cycle
        out[2] <= (count < 60) ? 1 : 0;  // 60% duty cycle
        out[3] <= (count < 80) ? 1 : 0;  // 80% duty cycle
    end

endmodule

pwm/pwm_tb.v
module pwm_tb;
    reg clk;
    wire [3:0] out;

    // Instantiate the PWM module
    pwm uut (
        .clk(clk),
        .out(out)
    );

    // Clock generation
    initial begin
        clk = 0;
        forever #5 clk = ~clk; // 10 time units per clock cycle
    end

    // Simulation control
    initial begin
        $dumpfile("pwm.vcd");
        $dumpvars(0, pwm_tb);

        // Run the simulation for some time
        #1000;
        $finish;
    end
endmodule

pwm/pwm.vcd
$date
	Tue Oct  1 22:45:48 2024
$end
$version
	Icarus Verilog
$end
$timescale
	1s
$end
$scope module pwm_tb $end
$var wire 4 ! out [3:0] $end
$var reg 1 " clk $end
$scope module uut $end
$var wire 1 " clk $end
$var reg 8 # count [7:0] $end
$var reg 4 $ out [3:0] $end
$upscope $end
$upscope $end
$enddefinitions $end
#0
$dumpvars
bx $
b0 #
0"
bx !
$end
#5
b1 #
b1111 !
b1111 $
1"
#10
0"
#15
b10 #
b1111 !
b1111 $
1"
#20
0"
#25
b11 #
b1111 !
b1111 $
1"
#30
0"
#35
b100 #
b1111 !
b1111 $
1"
#40
0"
#45
b101 #
b1111 !
b1111 $
1"
#50
0"
#55
b110 #
b1111 !
b1111 $
1"
#60
0"
#65
b111 #
b1111 !
b1111 $
1"
#70
0"
#75
b1000 #
b1111 !
b1111 $
1"
#80
0"
#85
b1001 #
b1111 !
b1111 $
1"
#90
0"
#95
b1010 #
b1111 !
b1111 $
1"
#100
0"
#105
b1011 #
b1111 !
b1111 $
1"
#110
0"
#115
b1100 #
b1111 !
b1111 $
1"
#120
0"
#125
b1101 #
b1111 !
b1111 $
1"
#130
0"
#135
b1110 #
b1111 !
b1111 $
1"
#140
0"
#145
b1111 #
b1111 !
b1111 $
1"
#150
0"
#155
b10000 #
b1111 !
b1111 $
1"
#160
0"
#165
b10001 #
b1111 !
b1111 $
1"
#170
0"
#175
b10010 #
b1111 !
b1111 $
1"
#180
0"
#185
b10011 #
b1111 !
b1111 $
1"
#190
0"
#195
b10100 #
b1111 !
b1111 $
1"
#200
0"
#205
b10101 #
b1110 !
b1110 $
1"
#210
0"
#215
b10110 #
b1110 !
b1110 $
1"
#220
0"
#225
b10111 #
b1110 !
b1110 $
1"
#230
0"
#235
b11000 #
b1110 !
b1110 $
1"
#240
0"
#245
b11001 #
b1110 !
b1110 $
1"
#250
0"
#255
b11010 #
b1110 !
b1110 $
1"
#260
0"
#265
b11011 #
b1110 !
b1110 $
1"
#270
0"
#275
b11100 #
b1110 !
b1110 $
1"
#280
0"
#285
b11101 #
b1110 !
b1110 $
1"
#290
0"
#295
b11110 #
b1110 !
b1110 $
1"
#300
0"
#305
b11111 #
b1110 !
b1110 $
1"
#310
0"
#315
b100000 #
b1110 !
b1110 $
1"
#320
0"
#325
b100001 #
b1110 !
b1110 $
1"
#330
0"
#335
b100010 #
b1110 !
b1110 $
1"
#340
0"
#345
b100011 #
b1110 !
b1110 $
1"
#350
0"
#355
b100100 #
b1110 !
b1110 $
1"
#360
0"
#365
b100101 #
b1110 !
b1110 $
1"
#370
0"
#375
b100110 #
b1110 !
b1110 $
1"
#380
0"
#385
b100111 #
b1110 !
b1110 $
1"
#390
0"
#395
b101000 #
b1110 !
b1110 $
1"
#400
0"
#405
b101001 #
b1100 !
b1100 $
1"
#410
0"
#415
b101010 #
b1100 !
b1100 $
1"
#420
0"
#425
b101011 #
b1100 !
b1100 $
1"
#430
0"
#435
b101100 #
b1100 !
b1100 $
1"
#440
0"
#445
b101101 #
b1100 !
b1100 $
1"
#450
0"
#455
b101110 #
b1100 !
b1100 $
1"
#460
0"
#465
b101111 #
b1100 !
b1100 $
1"
#470
0"
#475
b110000 #
b1100 !
b1100 $
1"
#480
0"
#485
b110001 #
b1100 !
b1100 $
1"
#490
0"
#495
b110010 #
b1100 !
b1100 $
1"
#500
0"
#505
b110011 #
b1100 !
b1100 $
1"
#510
0"
#515
b110100 #
b1100 !
b1100 $
1"
#520
0"
#525
b110101 #
b1100 !
b1100 $
1"
#530
0"
#535
b110110 #
b1100 !
b1100 $
1"
#540
0"
#545
b110111 #
b1100 !
b1100 $
1"
#550
0"
#555
b111000 #
b1100 !
b1100 $
1"
#560
0"
#565
b111001 #
b1100 !
b1100 $
1"
#570
0"
#575
b111010 #
b1100 !
b1100 $
1"
#580
0"
#585
b111011 #
b1100 !
b1100 $
1"
#590
0"
#595
b111100 #
b1100 !
b1100 $
1"
#600
0"
#605
b111101 #
b1000 !
b1000 $
1"
#610
0"
#615
b111110 #
b1000 !
b1000 $
1"
#620
0"
#625
b111111 #
b1000 !
b1000 $
1"
#630
0"
#635
b1000000 #
b1000 !
b1000 $
1"
#640
0"
#645
b1000001 #
b1000 !
b1000 $
1"
#650
0"
#655
b1000010 #
b1000 !
b1000 $
1"
#660
0"
#665
b1000011 #
b1000 !
b1000 $
1"
#670
0"
#675
b1000100 #
b1000 !
b1000 $
1"
#680
0"
#685
b1000101 #
b1000 !
b1000 $
1"
#690
0"
#695
b1000110 #
b1000 !
b1000 $
1"
#700
0"
#705
b1000111 #
b1000 !
b1000 $
1"
#710
0"
#715
b1001000 #
b1000 !
b1000 $
1"
#720
0"
#725
b1001001 #
b1000 !
b1000 $
1"
#730
0"
#735
b1001010 #
b1000 !
b1000 $
1"
#740
0"
#745
b1001011 #
b1000 !
b1000 $
1"
#750
0"
#755
b1001100 #
b1000 !
b1000 $
1"
#760
0"
#765
b1001101 #
b1000 !
b1000 $
1"
#770
0"
#775
b1001110 #
b1000 !
b1000 $
1"
#780
0"
#785
b1001111 #
b1000 !
b1000 $
1"
#790
0"
#795
b1010000 #
b1000 !
b1000 $
1"
#800
0"
#805
b1010001 #
b0 !
b0 $
1"
#810
0"
#815
b1010010 #
1"
#820
0"
#825
b1010011 #
1"
#830
0"
#835
b1010100 #
1"
#840
0"
#845
b1010101 #
1"
#850
0"
#855
b1010110 #
1"
#860
0"
#865
b1010111 #
1"
#870
0"
#875
b1011000 #
1"
#880
0"
#885
b1011001 #
1"
#890
0"
#895
b1011010 #
1"
#900
0"
#905
b1011011 #
1"
#910
0"
#915
b1011100 #
1"
#920
0"
#925
b1011101 #
1"
#930
0"
#935
b1011110 #
1"
#940
0"
#945
b1011111 #
1"
#950
0"
#955
b1100000 #
1"
#960
0"
#965
b1100001 #
1"
#970
0"
#975
b1100010 #
1"
#980
0"
#985
b1100011 #
1"
#990
0"
#995
b0 #
1"
