counter/modnCounter.v
module modnCounter #(
    parameter N = 15,      // Modulo value
    parameter WIDTH = 4    // Bit-width of the counter
) (
    input clk, resetn,
    output reg [WIDTH-1:0] counter
);
    always @(posedge clk) begin
        if (!resetn) begin
            counter <= {WIDTH{1'b0}};
        end else begin
            if (counter == N) begin
                counter <= {WIDTH{1'b0}};
            end else begin
                counter <= counter + 4'h1;
            end
        end
    end
endmodule

counter/modnCounter_tb.v
`timescale 1ns/1ps

module modnCounter_tb;
    parameter N = 15;
    parameter WIDTH = 4;

    reg clk, resetn;
    wire [WIDTH-1:0] counter;  // Declare as multi-bit wire to match the DUT output width

    // Instantiate the Unit Under Test (UUT)
    modnCounter uut (
        .clk(clk),
        .resetn(resetn),
        .counter(counter)
    );

    // Clock generation
    initial begin
        clk = 0;
        forever #5 clk = ~clk;  // Toggle clock every 10 ns
    end

    // Reset logic
    initial begin
        resetn = 0;  // Assert reset (active low)
        #10 resetn = 1;  // Release reset after 20 ns
    end

    // Simulation stop
    initial begin
        #200;  // Run simulation for 200 ns
        $finish;
    end

    // Monitor and dump signals
    initial begin
        $monitor("Time = %0t, resetn = %0b, counter = %0h", $time, resetn, counter);
        $dumpfile("counter.vcd");
        $dumpvars(0, modnCounter_tb);
    end
endmodule

counter/counter.vcd
$date
	Fri Sep 27 13:42:06 2024
$end
$version
	Icarus Verilog
$end
$timescale
	1ps
$end
$scope module modnCounter_tb $end
$var wire 4 ! counter [3:0] $end
$var reg 1 " clk $end
$var reg 1 # resetn $end
$scope module uut $end
$var wire 1 " clk $end
$var wire 1 # resetn $end
$var reg 4 $ counter [3:0] $end
$upscope $end
$upscope $end
$enddefinitions $end
#0
$dumpvars
bx $
0#
0"
bx !
$end
#5000
b0 !
b0 $
1"
#10000
0"
1#
#15000
b1 !
b1 $
1"
#20000
0"
#25000
b10 !
b10 $
1"
#30000
0"
#35000
b11 !
b11 $
1"
#40000
0"
#45000
b100 !
b100 $
1"
#50000
0"
#55000
b101 !
b101 $
1"
#60000
0"
#65000
b110 !
b110 $
1"
#70000
0"
#75000
b111 !
b111 $
1"
#80000
0"
#85000
b1000 !
b1000 $
1"
#90000
0"
#95000
b1001 !
b1001 $
1"
#100000
0"
#105000
b1010 !
b1010 $
1"
#110000
0"
#115000
b1011 !
b1011 $
1"
#120000
0"
#125000
b1100 !
b1100 $
1"
#130000
0"
#135000
b1101 !
b1101 $
1"
#140000
0"
#145000
b1110 !
b1110 $
1"
#150000
0"
#155000
b1111 !
b1111 $
1"
#160000
0"
#165000
b0 !
b0 $
1"
#170000
0"
#175000
b1 !
b1 $
1"
#180000
0"
#185000
b10 !
b10 $
1"
#190000
0"
#195000
b11 !
b11 $
1"
