clock/digitalclock.v
`timescale 1ns / 1ps 

module digitalclock(
    input Clk_1sec,   // Clock with 1 Hz frequency
    input reset,      // Active high reset
    output reg [5:0] seconds,
    output reg [5:0] minutes,
    output reg [4:0] hours  // 5 bits can represent hours 0 to 31
);
    // Constants for maximum values
    parameter SECONDS_MAX = 6'd59;
    parameter MINUTES_MAX = 6'd59;
    parameter HOURS_MAX = 5'd23; // Max for 24-hour format

    // Execute the always block on the positive edge of Clk_1sec or reset
    always @(posedge Clk_1sec or posedge reset) begin
        if (reset) begin  // Check for active high reset
            seconds <= 6'b0;  
            minutes <= 6'b0;  
            hours   <= 5'b0;   
        end else begin
            seconds <= seconds + 1;  
            if (seconds == SECONDS_MAX) begin
                seconds <= 6'b0;  
                minutes <= minutes + 6'd1;  
                if (minutes == MINUTES_MAX) begin  
                    minutes <= 6'b0;  
                    hours <= hours + 6'd1; 
                    if (hours == HOURS_MAX) begin
                        hours <= 5'b0; // Reset hours after reaching 24
                    end                   
                end
            end
        end
    end
endmodule

clock/digitalclock_tb.v
module digitalclock_tb; 
    // Inputs
    reg Clk_1sec; 
    reg reset; 

    // Outputs
    wire [5:0] seconds; 
    wire [5:0] minutes; 
    wire [4:0] hours; 

    // Instantiate the Unit Under Test (UUT) 
    digitalclock uut (
        .Clk_1sec(Clk_1sec), 
        .reset(reset), 
        .seconds(seconds), 
        .minutes(minutes), 
        .hours(hours) 
    ); 

    // Generating the Clock with 1 Hz frequency
    initial Clk_1sec = 0; 
    always #0.5 Clk_1sec = ~Clk_1sec;  // 1 Hz clock (1 second period)

    // Testbench stimulus
    initial begin 
        reset = 1; 
        // Wait for global reset to finish 
        #1; 
        reset = 0; 

        // Run the simulation for a sufficient time to observe behavior
        #86400;  // Run for 86400 seconds (24 hours)
        $finish; 
    end 

    // Monitor outputs
    initial begin
        // Print every change in hours
        $monitor("At time %0t: reset = %b, seconds = %d, minutes = %d, hours = %d", 
                 $time, reset, seconds, minutes, hours);
    end 

    // Dump waveform
    initial begin
        $dumpfile("digital_clock.vcd");  // Specify the VCD file name
        $dumpvars(0, digitalclock_tb);          // Dump all variables in the tb_clock module
    end 
endmodule

clock/digital_clock.vcd
$date
	Wed Sep 25 21:11:35 2024
$end
$version
	Icarus Verilog
$end
$timescale
	1ps
$end
$scope module digitalclock_tb $end
$var wire 6 ! seconds [5:0] $end
$var wire 6 " minutes [5:0] $end
$var wire 5 # hours [4:0] $end
$var reg 1 $ Clk_1sec $end
$var reg 1 % reset $end
$scope module uut $end
$var wire 1 $ Clk_1sec $end
$var wire 1 % reset $end
$var reg 5 & hours [4:0] $end
$var reg 6 ' minutes [5:0] $end
$var reg 6 ( seconds [5:0] $end
$upscope $end
$upscope $end
$enddefinitions $end
#0
$dumpvars
b0 (
b0 '
b0 &
1%
0$
b0 #
b0 "
b0 !
$end
#500
1$
#1000
0$
0%
#1500
b1 !
b1 (
1$
#2000
0$
#2500
b10 !
b10 (
1$
#3000
0$
#3500
b11 !
b11 (
1$
#4000
0$
#4500
b100 !
b100 (
1$
#5000
0$
#5500
b101 !
b101 (
1$
#6000
0$
#6500
b110 !
b110 (
1$
#7000
0$
#7500
b111 !
b111 (
1$
#8000
0$
#8500
b1000 !
b1000 (
1$
#9000
0$
#9500
b1001 !
b1001 (
1$
#10000
0$
#10500
b1010 !
b1010 (
1$
#11000
0$
#11500
b1011 !
b1011 (
1$
#12000
0$
#12500
b1100 !
b1100 (
1$
#13000
0$
#13500
b1101 !
b1101 (
1$
#14000
0$
#14500
b1110 !
b1110 (
1$
#15000
0$
#15500
b1111 !
b1111 (
1$
#16000
0$
#16500
b10000 !
b10000 (
1$
#17000
0$
#17500
b10001 !
b10001 (
1$
#18000
0$
#18500
b10010 !
b10010 (
1$
#19000
0$
#19500
b10011 !
b10011 (
1$
#20000
0$
#20500
b10100 !
b10100 (
1$
#21000
0$
#21500
b10101 !
b10101 (
1$
#22000
0$
#22500
b10110 !
b10110 (
1$
#23000
0$
#23500
b10111 !
b10111 (
1$
#24000
0$
#24500
b11000 !
b11000 (
1$
#25000
0$
#25500
b11001 !
b11001 (
1$
#26000
0$
#26500
b11010 !
b11010 (
1$
#27000
0$
#27500
b11011 !
b11011 (
1$
#28000
0$
#28500
b11100 !
b11100 (
1$
#29000
0$
#29500
b11101 !
b11101 (
1$
#30000
0$
#30500
b11110 !
b11110 (
1$
#31000
0$
#31500
b11111 !
b11111 (
1$
#32000
0$
#32500
b100000 !
b100000 (
1$
#33000
0$
#33500
b100001 !
b100001 (
1$
#34000
0$
#34500
b100010 !
b100010 (
1$
#35000
0$
#35500
b100011 !
b100011 (
1$
#36000
0$
#36500
b100100 !
b100100 (
1$
#37000
0$
#37500
b100101 !
b100101 (
1$
#38000
0$
#38500
b100110 !
b100110 (
1$
#39000
0$
#39500
b100111 !
b100111 (
1$
#40000
0$
#40500
b101000 !
b101000 (
1$
#41000
0$
#41500
b101001 !
b101001 (
1$
#42000
0$
#42500
b101010 !
b101010 (
1$
#43000
0$
#43500
b101011 !
b101011 (
1$
#44000
0$
#44500
b101100 !
b101100 (
1$
#45000
0$
#45500
b101101 !
b101101 (
1$
#46000
0$
#46500
b101110 !
b101110 (
1$
#47000
0$
#47500
b101111 !
b101111 (
1$
#48000
0$
#48500
b110000 !
b110000 (
1$
#49000
0$
#49500
b110001 !
b110001 (
1$
#50000
0$
#50500
b110010 !
b110010 (
1$
#51000
0$
#51500
b110011 !
b110011 (
1$
#52000
0$
#52500
b110100 !
b110100 (
1$
#53000
0$
#53500
b110101 !
b110101 (
1$
#54000
0$
#54500
b110110 !
b110110 (
1$
#55000
0$
#55500
b110111 !
b110111 (
1$
#56000
0$
#56500
b111000 !
b111000 (
1$
#57000
0$
#57500
b111001 !
b111001 (
1$
#58000
0$
#58500
b111010 !
b111010 (
1$
#59000
0$
#59500
b111011 !
b111011 (
1$
#60000
0$
#60500
b1 "
b1 '
b0 !
b0 (
1$
#61000
0$
#61500
b1 !
b1 (
1$
#62000
0$
#62500
b10 !
b10 (
1$
#63000
0$
#63500
b11 !
b11 (
1$
#64000
0$
#64500
b100 !
b100 (
1$
#65000
0$
#65500
b101 !
b101 (
1$
#66000
0$
#66500
b110 !
b110 (
1$
#67000
0$
#67500
b111 !
b111 (
1$
#68000
0$
#68500
b1000 !
b1000 (
1$
#69000
0$
#69500
b1001 !
b1001 (
1$
#70000
0$
#70500
b1010 !
b1010 (
1$
#71000
0$
#71500
b1011 !
b1011 (
1$
#72000
0$
#72500
b1100 !
b1100 (
1$
#73000
0$
#73500
b1101 !
b1101 (
1$
#74000
0$
#74500
b1110 !
b1110 (
1$
#75000
0$
#75500
b1111 !
b1111 (
1$
#76000
0$
#76500
b10000 !
b10000 (
1$
#77000
0$
#77500
b10001 !
b10001 (
1$
#78000
0$
#78500
b10010 !
b10010 (
1$
#79000
0$
#79500
b10011 !
b10011 (
1$
#80000
0$
#80500
b10100 !
b10100 (
1$
#81000
0$
#81500
b10101 !
b10101 (
1$
#82000
0$
#82500
b10110 !
b10110 (
1$
#83000
0$
#83500
b10111 !
b10111 (
1$
#84000
0$
#84500
b11000 !
b11000 (
1$
#85000
0$
#85500
b11001 !
b11001 (
1$
#86000
0$
#86500
b11010 !
b11010 (
1$
#87000
0$
#87500
b11011 !
b11011 (
1$
#88000
0$
#88500
b11100 !
b11100 (
1$
#89000
0$
#89500
b11101 !
b11101 (
1$
#90000
0$
#90500
b11110 !
b11110 (
1$
#91000
0$
#91500
b11111 !
b11111 (
1$
#92000
0$
#92500
b100000 !
b100000 (
1$
#93000
0$
#93500
b100001 !
b100001 (
1$
#94000
0$
#94500
b100010 !
b100010 (
1$
#95000
0$
#95500
b100011 !
b100011 (
1$
#96000
0$
#96500
b100100 !
b100100 (
1$
#97000
0$
#97500
b100101 !
b100101 (
1$
#98000
0$
#98500
b100110 !
b100110 (
1$
#99000
0$
#99500
b100111 !
b100111 (
1$
#100000
0$
#100500
b101000 !
b101000 (
1$
#101000
0$
#101500
b101001 !
b101001 (
1$
#102000
0$
#102500
b101010 !
b101010 (
1$
#103000
0$
#103500
b101011 !
b101011 (
1$
#104000
0$
#104500
b101100 !
b101100 (
1$
#105000
0$
#105500
b101101 !
b101101 (
1$
#106000
0$
#106500
b101110 !
b101110 (
1$
#107000
0$
#107500
b101111 !
b101111 (
1$
#108000
0$
#108500
b110000 !
b110000 (
1$
#109000
0$
#109500
b110001 !
b110001 (
1$
#110000
0$
#110500
b110010 !
b110010 (
1$
#111000
0$
#111500
b110011 !
b110011 (
1$
#112000
0$
#112500
b110100 !
b110100 (
1$
#113000
0$
#113500
b110101 !
b110101 (
1$
#114000
0$
#114500
b110110 !
b110110 (
1$
#115000
0$
#115500
b110111 !
b110111 (
1$
#116000
0$
#116500
b111000 !
b111000 (
1$
#117000
0$
#117500
b111001 !
b111001 (
1$
#118000
0$
#118500
b111010 !
b111010 (
1$
#119000
0$
#119500
b111011 !
b111011 (
1$
#120000
0$
#120500
b10 "
b10 '
b0 !
b0 (
1$
#121000
0$
#121500
b1 !
b1 (
1$
#122000
0$
#122500
b10 !
b10 (
1$
#123000
0$
#123500
b11 !
b11 (
1$
#124000
0$
#124500
b100 !
b100 (
1$
#125000
0$
#125500
b101 !
b101 (
1$
#126000
0$
#126500
b110 !
b110 (
1$
#127000
0$
#127500
b111 !
b111 (
1$
#128000
0$
#128500
b1000 !
b1000 (
1$
#129000
0$
#129500
b1001 !
b1001 (
1$
#130000
0$
#130500
b1010 !
b1010 (
1$
#131000
0$
#131500
b1011 !
b1011 (
1$
#132000
0$
#132500
b1100 !
b1100 (
1$
#133000
0$
#133500
b1101 !
b1101 (
1$
#134000
0$
#134500
b1110 !
b1110 (
1$
#135000
0$
#135500
b1111 !
b1111 (
1$
#136000
0$
#136500
b10000 !
b10000 (
1$
#137000
0$
#137500
b10001 !
b10001 (
1$
#138000
0$
#138500
b10010 !
b10010 (
1$
#139000
0$
#139500
b10011 !
b10011 (
1$
#140000
0$
#140500
b10100 !
b10100 (
1$
#141000
0$
#141500
b10101 !
b10101 (
1$
#142000
0$
#142500
b10110 !
b10110 (
1$
#143000
0$
#143500
b10111 !
b10111 (
1$
#144000
0$
#144500
b11000 !
b11000 (
1$
#145000
0$
#145500
b11001 !
b11001 (
1$
#146000
0$
#146500
b11010 !
b11010 (
1$
#147000
0$
#147500
b11011 !
b11011 (
1$
#148000
0$
#148500
b11100 !
b11100 (
1$
#149000
0$
#149500
b11101 !
b11101 (
1$
#150000
0$
#150500
b11110 !
b11110 (
1$
#151000
0$
#151500
b11111 !
b11111 (
1$
#152000
0$
#152500
b100000 !
b100000 (
1$
#153000
0$
#153500
b100001 !
b100001 (
1$
#154000
0$
#154500
b100010 !
b100010 (
1$
#155000
0$
#155500
b100011 !
b100011 (
1$
#156000
0$
#156500
b100100 !
b100100 (
1$
#157000
0$
#157500
b100101 !
b100101 (
1$
#158000
0$
#158500
b100110 !
b100110 (
1$
#159000
0$
#159500
b100111 !
b100111 (
1$
#160000
0$
#160500
b101000 !
b101000 (
1$
#161000
0$
#161500
b101001 !
b101001 (
1$
#162000
0$
#162500
b101010 !
b101010 (
1$
#163000
0$
#163500
b101011 !
b101011 (
1$
#164000
0$
#164500
b101100 !
b101100 (
1$
#165000
0$
#165500
b101101 !
b101101 (
1$
#166000
0$
#166500
b101110 !
b101110 (
1$
#167000
0$
#167500
b101111 !
b101111 (
1$
#168000
0$
#168500
b110000 !
b110000 (
1$
#169000
0$
#169500
b110001 !
b110001 (
1$
#170000
0$
#170500
b110010 !
b110010 (
1$
#171000
0$
#171500
b110011 !
b110011 (
1$
#172000
0$
#172500
b110100 !
b110100 (
1$
#173000
0$
#173500
b110101 !
b110101 (
1$
#174000
0$
#174500
b110110 !
b110110 (
1$
#175000
0$
#175500
b110111 !
b110111 (
1$
#176000
0$
#176500
b111000 !
b111000 (
1$
#177000
0$
#177500
b111001 !
b111001 (
1$
#178000
0$
#178500
b111010 !
b111010 (
1$
#179000
0$
#179500
b111011 !
b111011 (
1$
#180000
0$
#180500
b11 "
b11 '
b0 !
b0 (
1$
#181000
0$
#181500
b1 !
b1 (
1$
#182000
0$
#182500
b10 !
b10 (
1$
#183000
0$
#183500
b11 !
b11 (
1$
#184000
0$
#184500
b100 !
b100 (
1$
#185000
0$
#185500
b101 !
b101 (
1$
#186000
0$
#186500
b110 !
b110 (
1$
#187000
0$
#187500
b111 !
b111 (
1$
#188000
0$
#188500
b1000 !
b1000 (
1$
#189000
0$
#189500
b1001 !
b1001 (
1$
#190000
0$
#190500
b1010 !
b1010 (
1$
#191000
0$
#191500
b1011 !
b1011 (
1$
#192000
0$
#192500
b1100 !
b1100 (
1$
#193000
0$
#193500
b1101 !
b1101 (
1$
#194000
0$
#194500
b1110 !
b1110 (
1$
#195000
0$
#195500
b1111 !
b1111 (
1$
#196000
0$
#196500
b10000 !
b10000 (
1$
#197000
0$
#197500
b10001 !
b10001 (
1$
#198000
0$
#198500
b10010 !
b10010 (
1$
#199000
0$
#199500
b10011 !
b10011 (
1$
#200000
0$
#200500
b10100 !
b10100 (
1$
#201000
0$
#201500
b10101 !
b10101 (
1$
#202000
0$
#202500
b10110 !
b10110 (
1$
#203000
0$
#203500
b10111 !
b10111 (
1$
#204000
0$
#204500
b11000 !
b11000 (
1$
#205000
0$
#205500
b11001 !
b11001 (
1$
#206000
0$
#206500
b11010 !
b11010 (
1$
#207000
0$
#207500
b11011 !
b11011 (
1$
#208000
0$
#208500
b11100 !
b11100 (
1$
#209000
0$
#209500
b11101 !
b11101 (
1$
#210000
0$
#210500
b11110 !
b11110 (
1$
#211000
0$
#211500
b11111 !
b11111 (
1$
#212000
0$
#212500
b100000 !
b100000 (
1$
#213000
0$
#213500
b100001 !
b100001 (
1$
#214000
0$
#214500
b100010 !
b100010 (
1$
#215000
0$
#215500
b100011 !
b100011 (
1$
#216000
0$
#216500
b100100 !
b100100 (
1$
#217000
0$
#217500
b100101 !
b100101 (
1$
#218000
0$
#218500
b100110 !
b100110 (
1$
#219000
0$
#219500
b100111 !
b100111 (
1$
#220000
0$
#220500
b101000 !
b101000 (
1$
#221000
0$
#221500
b101001 !
b101001 (
1$
#222000
0$
#222500
b101010 !
b101010 (
1$
#223000
0$
#223500
b101011 !
b101011 (
1$
#224000
0$
#224500
b101100 !
b101100 (
1$
#225000
0$
#225500
b101101 !
b101101 (
1$
#226000
0$
#226500
b101110 !
b101110 (
1$
#227000
0$
#227500
b101111 !
b101111 (
1$
#228000
0$
#228500
b110000 !
b110000 (
1$
#229000
0$
#229500
b110001 !
b110001 (
1$
#230000
0$
#230500
b110010 !
b110010 (
1$
#231000
0$
#231500
b110011 !
b110011 (
1$
#232000
0$
#232500
b110100 !
b110100 (
1$
#233000
0$
#233500
b110101 !
b110101 (
1$
#234000
0$
#234500
b110110 !
b110110 (
1$
#235000
0$
#235500
b110111 !
b110111 (
1$
#236000
0$
#236500
b111000 !
b111000 (
1$
#237000
0$
#237500
b111001 !
b111001 (
1$
#238000
0$
#238500
b111010 !
b111010 (
1$
#239000
0$
#239500
b111011 !
b111011 (
1$
#240000
0$
#240500
b100 "
b100 '
b0 !
b0 (
1$
#241000
0$
#241500
b1 !
b1 (
1$
#242000
0$
#242500
b10 !
b10 (
1$
#243000
0$
#243500
b11 !
b11 (
1$
#244000
0$
#244500
b100 !
b100 (
1$
#245000
0$
#245500
b101 !
b101 (
1$
#246000
0$
#246500
b110 !
b110 (
1$
#247000
0$
#247500
b111 !
b111 (
1$
#248000
0$
#248500
b1000 !
b1000 (
1$
#249000
0$
#249500
b1001 !
b1001 (
1$
#250000
0$
#250500
b1010 !
b1010 (
1$
#251000
0$
#251500
b1011 !
b1011 (
1$
#252000
0$
#252500
b1100 !
b1100 (
1$
#253000
0$
#253500
b1101 !
b1101 (
1$
#254000
0$
#254500
b1110 !
b1110 (
1$
#255000
0$
#255500
b1111 !
b1111 (
1$
#256000
0$
#256500
b10000 !
b10000 (
1$
#257000
0$
#257500
b10001 !
b10001 (
1$
#258000
0$
#258500
b10010 !
b10010 (
1$
#259000
0$
#259500
b10011 !
b10011 (
1$
#260000
0$
#260500
b10100 !
b10100 (
1$
#261000
0$
#261500
b10101 !
b10101 (
1$
#262000
0$
#262500
b10110 !
b10110 (
1$
#263000
0$
#263500
b10111 !
b10111 (
1$
#264000
0$
#264500
b11000 !
b11000 (
1$
#265000
0$
#265500
b11001 !
b11001 (
1$
#266000
0$
#266500
b11010 !
b11010 (
1$
#267000
0$
#267500
b11011 !
b11011 (
1$
#268000
0$
#268500
b11100 !
b11100 (
1$
#269000
0$
#269500
b11101 !
b11101 (
1$
#270000
0$
#270500
b11110 !
b11110 (
1$
#271000
0$
#271500
b11111 !
b11111 (
1$
#272000
0$
#272500
b100000 !
b100000 (
1$
#273000
0$
#273500
b100001 !
b100001 (
1$
#274000
0$
#274500
b100010 !
b100010 (
1$
#275000
0$
#275500
b100011 !
b100011 (
1$
#276000
0$
#276500
b100100 !
b100100 (
1$
#277000
0$
#277500
b100101 !
b100101 (
1$
#278000
0$
#278500
b100110 !
b100110 (
1$
#279000
0$
#279500
b100111 !
b100111 (
1$
#280000
0$
#280500
b101000 !
b101000 (
1$
#281000
0$
#281500
b101001 !
b101001 (
1$
#282000
0$
#282500
b101010 !
b101010 (
1$
#283000
0$
#283500
b101011 !
b101011 (
1$
#284000
0$
#284500
b101100 !
b101100 (
1$
#285000
0$
#285500
b101101 !
b101101 (
1$
#286000
0$
#286500
b101110 !
b101110 (
1$
#287000
0$
#287500
b101111 !
b101111 (
1$
#288000
0$
#288500
b110000 !
b110000 (
1$
#289000
0$
#289500
b110001 !
b110001 (
1$
#290000
0$
#290500
b110010 !
b110010 (
1$
#291000
0$
#291500
b110011 !
b110011 (
1$
#292000
0$
#292500
b110100 !
b110100 (
1$
#293000
0$
#293500
b110101 !
b110101 (
1$
#294000
0$
#294500
b110110 !
b110110 (
1$
#295000
0$
#295500
b110111 !
b110111 (
1$
#296000
0$
#296500
b111000 !
b111000 (
1$
#297000
0$
#297500
b111001 !
b111001 (
1$
#298000
0$
#298500
b111010 !
b111010 (
1$
#299000
0$
#299500
b111011 !
b111011 (
1$
#300000
0$
#300500
b101 "
b101 '
b0 !
b0 (
1$
#301000
0$
#301500
b1 !
b1 (
1$
#302000
0$
#302500
b10 !
b10 (
1$
#303000
0$
#303500
b11 !
b11 (
1$
#304000
0$
#304500
b100 !
b100 (
1$
#305000
0$
#305500
b101 !
b101 (
1$
#306000
0$
#306500
b110 !
b110 (
1$
#307000
0$
#307500
b111 !
b111 (
1$
#308000
0$
#308500
b1000 !
b1000 (
1$
#309000
0$
#309500
b1001 !
b1001 (
1$
#310000
0$
#310500
b1010 !
b1010 (
1$
#311000
0$
#311500
b1011 !
b1011 (
1$
#312000
0$
#312500
b1100 !
b1100 (
1$
#313000
0$
#313500
b1101 !
b1101 (
1$
#314000
0$
#314500
b1110 !
b1110 (
1$
#315000
0$
#315500
b1111 !
b1111 (
1$
#316000
0$
#316500
b10000 !
b10000 (
1$
#317000
0$
#317500
b10001 !
b10001 (
1$
#318000
0$
#318500
b10010 !
b10010 (
1$
#319000
0$
#319500
b10011 !
b10011 (
1$
#320000
0$
#320500
b10100 !
b10100 (
1$
#321000
0$
#321500
b10101 !
b10101 (
1$
#322000
0$
#322500
b10110 !
b10110 (
1$
#323000
0$
#323500
b10111 !
b10111 (
1$
#324000
0$
#324500
b11000 !
b11000 (
1$
#325000
0$
#325500
b11001 !
b11001 (
1$
#326000
0$
#326500
b11010 !
b11010 (
1$
#327000
0$
#327500
b11011 !
b11011 (
1$
#328000
0$
#328500
b11100 !
b11100 (
1$
#329000
0$
#329500
b11101 !
b11101 (
1$
#330000
0$
#330500
b11110 !
b11110 (
1$
#331000
0$
#331500
b11111 !
b11111 (
1$
#332000
0$
#332500
b100000 !
b100000 (
1$
#333000
0$
#333500
b100001 !
b100001 (
1$
#334000
0$
#334500
b100010 !
b100010 (
1$
#335000
0$
#335500
b100011 !
b100011 (
1$
#336000
0$
#336500
b100100 !
b100100 (
1$
#337000
0$
#337500
b100101 !
b100101 (
1$
#338000
0$
#338500
b100110 !
b100110 (
1$
#339000
0$
#339500
b100111 !
b100111 (
1$
#340000
0$
#340500
b101000 !
b101000 (
1$
#341000
0$
#341500
b101001 !
b101001 (
1$
#342000
0$
#342500
b101010 !
b101010 (
1$
#343000
0$
#343500
b101011 !
b101011 (
1$
#344000
0$
#344500
b101100 !
b101100 (
1$
#345000
0$
#345500
b101101 !
b101101 (
1$
#346000
0$
#346500
b101110 !
b101110 (
1$
#347000
0$
#347500
b101111 !
b101111 (
1$
#348000
0$
#348500
b110000 !
b110000 (
1$
#349000
0$
#349500
b110001 !
b110001 (
1$
#350000
0$
#350500
b110010 !
b110010 (
1$
#351000
0$
#351500
b110011 !
b110011 (
1$
#352000
0$
#352500
b110100 !
b110100 (
1$
#353000
0$
#353500
b110101 !
b110101 (
1$
#354000
0$
#354500
b110110 !
b110110 (
1$
#355000
0$
#355500
b110111 !
b110111 (
1$
#356000
0$
#356500
b111000 !
b111000 (
1$
#357000
0$
#357500
b111001 !
b111001 (
1$
#358000
0$
#358500
b111010 !
b111010 (
1$
#359000
0$
#359500
b111011 !
b111011 (
1$
#360000
0$
#360500
b110 "
b110 '
b0 !
b0 (
1$
#361000
0$
#361500
b1 !
b1 (
1$
#362000
0$
#362500
b10 !
b10 (
1$
#363000
0$
#363500
b11 !
b11 (
1$
#364000
0$
#364500
b100 !
b100 (
1$
#365000
0$
#365500
b101 !
b101 (
1$
#366000
0$
#366500
b110 !
b110 (
1$
#367000
0$
#367500
b111 !
b111 (
1$
#368000
0$
#368500
b1000 !
b1000 (
1$
#369000
0$
#369500
b1001 !
b1001 (
1$
#370000
0$
#370500
b1010 !
b1010 (
1$
#371000
0$
#371500
b1011 !
b1011 (
1$
#372000
0$
#372500
b1100 !
b1100 (
1$
#373000
0$
#373500
b1101 !
b1101 (
1$
#374000
0$
#374500
b1110 !
b1110 (
1$
#375000
0$
#375500
b1111 !
b1111 (
1$
#376000
0$
#376500
b10000 !
b10000 (
1$
#377000
0$
#377500
b10001 !
b10001 (
1$
#378000
0$
#378500
b10010 !
b10010 (
1$
#379000
0$
#379500
b10011 !
b10011 (
1$
#380000
0$
#380500
b10100 !
b10100 (
1$
#381000
0$
#381500
b10101 !
b10101 (
1$
#382000
0$
#382500
b10110 !
b10110 (
1$
#383000
0$
#383500
b10111 !
b10111 (
1$
#384000
0$
#384500
b11000 !
b11000 (
1$
#385000
0$
#385500
b11001 !
b11001 (
1$
#386000
0$
#386500
b11010 !
b11010 (
1$
#387000
0$
#387500
b11011 !
b11011 (
1$
#388000
0$
#388500
b11100 !
b11100 (
1$
#389000
0$
#389500
b11101 !
b11101 (
1$
#390000
0$
#390500
b11110 !
b11110 (
1$
#391000
0$
#391500
b11111 !
b11111 (
1$
#392000
0$
#392500
b100000 !
b100000 (
1$
#393000
0$
#393500
b100001 !
b100001 (
1$
#394000
0$
#394500
b100010 !
b100010 (
1$
#395000
0$
#395500
b100011 !
b100011 (
1$
#396000
0$
#396500
b100100 !
b100100 (
1$
#397000
0$
#397500
b100101 !
b100101 (
1$
#398000
0$
#398500
b100110 !
b100110 (
1$
#399000
0$
#399500
b100111 !
b100111 (
1$
#400000
0$
#400500
b101000 !
b101000 (
1$
#401000
0$
#401500
b101001 !
b101001 (
1$
#402000
0$
#402500
b101010 !
b101010 (
1$
#403000
0$
#403500
b101011 !
b101011 (
1$
#404000
0$
#404500
b101100 !
b101100 (
1$
#405000
0$
#405500
b101101 !
b101101 (
1$
#406000
0$
#406500
b101110 !
b101110 (
1$
#407000
0$
#407500
b101111 !
b101111 (
1$
#408000
0$
#408500
b110000 !
b110000 (
1$
#409000
0$
#409500
b110001 !
b110001 (
1$
#410000
0$
#410500
b110010 !
b110010 (
1$
#411000
0$
#411500
b110011 !
b110011 (
1$
#412000
0$
#412500
b110100 !
b110100 (
1$
#413000
0$
#413500
b110101 !
b110101 (
1$
#414000
0$
#414500
b110110 !
b110110 (
1$
#415000
0$
#415500
b110111 !
b110111 (
1$
#416000
0$
#416500
b111000 !
b111000 (
1$
#417000
0$
#417500
b111001 !
b111001 (
1$
#418000
0$
#418500
b111010 !
b111010 (
1$
#419000
0$
#419500
b111011 !
b111011 (
1$
#420000
0$
#420500
b111 "
b111 '
b0 !
b0 (
1$
#421000
0$
#421500
b1 !
b1 (
1$
#422000
0$
#422500
b10 !
b10 (
1$
#423000
0$
#423500
b11 !
b11 (
1$
#424000
0$
#424500
b100 !
b100 (
1$
#425000
0$
#425500
b101 !
b101 (
1$
#426000
0$
#426500
b110 !
b110 (
1$
#427000
0$
#427500
b111 !
b111 (
1$
#428000
0$
#428500
b1000 !
b1000 (
1$
#429000
0$
#429500
b1001 !
b1001 (
1$
#430000
0$
#430500
b1010 !
b1010 (
1$
#431000
0$
#431500
b1011 !
b1011 (
1$
#432000
0$
#432500
b1100 !
b1100 (
1$
#433000
0$
#433500
b1101 !
b1101 (
1$
#434000
0$
#434500
b1110 !
b1110 (
1$
#435000
0$
#435500
b1111 !
b1111 (
1$
#436000
0$
#436500
b10000 !
b10000 (
1$
#437000
0$
#437500
b10001 !
b10001 (
1$
#438000
0$
#438500
b10010 !
b10010 (
1$
#439000
0$
#439500
b10011 !
b10011 (
1$
#440000
0$
#440500
b10100 !
b10100 (
1$
#441000
0$
#441500
b10101 !
b10101 (
1$
#442000
0$
#442500
b10110 !
b10110 (
1$
#443000
0$
#443500
b10111 !
b10111 (
1$
#444000
0$
#444500
b11000 !
b11000 (
1$
#445000
0$
#445500
b11001 !
b11001 (
1$
#446000
0$
#446500
b11010 !
b11010 (
1$
#447000
0$
#447500
b11011 !
b11011 (
1$
#448000
0$
#448500
b11100 !
b11100 (
1$
#449000
0$
#449500
b11101 !
b11101 (
1$
#450000
0$
#450500
b11110 !
b11110 (
1$
#451000
0$
#451500
b11111 !
b11111 (
1$
#452000
0$
#452500
b100000 !
b100000 (
1$
#453000
0$
#453500
b100001 !
b100001 (
1$
#454000
0$
#454500
b100010 !
b100010 (
1$
#455000
0$
#455500
b100011 !
b100011 (
1$
#456000
0$
#456500
b100100 !
b100100 (
1$
#457000
0$
#457500
b100101 !
b100101 (
1$
#458000
0$
#458500
b100110 !
b100110 (
1$
#459000
0$
#459500
b100111 !
b100111 (
1$
#460000
0$
#460500
b101000 !
b101000 (
1$
#461000
0$
#461500
b101001 !
b101001 (
1$
#462000
0$
#462500
b101010 !
b101010 (
1$
#463000
0$
#463500
b101011 !
b101011 (
1$
#464000
0$
#464500
b101100 !
b101100 (
1$
#465000
0$
#465500
b101101 !
b101101 (
1$
#466000
0$
#466500
b101110 !
b101110 (
1$
#467000
0$
#467500
b101111 !
b101111 (
1$
#468000
0$
#468500
b110000 !
b110000 (
1$
#469000
0$
#469500
b110001 !
b110001 (
1$
#470000
0$
#470500
b110010 !
b110010 (
1$
#471000
0$
#471500
b110011 !
b110011 (
1$
#472000
0$
#472500
b110100 !
b110100 (
1$
#473000
0$
#473500
b110101 !
b110101 (
1$
#474000
0$
#474500
b110110 !
b110110 (
1$
#475000
0$
#475500
b110111 !
b110111 (
1$
#476000
0$
#476500
b111000 !
b111000 (
1$
#477000
0$
#477500
b111001 !
b111001 (
1$
#478000
0$
#478500
b111010 !
b111010 (
1$
#479000
0$
#479500
b111011 !
b111011 (
1$
#480000
0$
#480500
b1000 "
b1000 '
b0 !
b0 (
1$
#481000
0$
#481500
b1 !
b1 (
1$
#482000
0$
#482500
b10 !
b10 (
1$
#483000
0$
#483500
b11 !
b11 (
1$
#484000
0$
#484500
b100 !
b100 (
1$
#485000
0$
#485500
b101 !
b101 (
1$
#486000
0$
#486500
b110 !
b110 (
1$
#487000
0$
#487500
b111 !
b111 (
1$
#488000
0$
#488500
b1000 !
b1000 (
1$
#489000
0$
#489500
b1001 !
b1001 (
1$
#490000
0$
#490500
b1010 !
b1010 (
1$
#491000
0$
#491500
b1011 !
b1011 (
1$
#492000
0$
#492500
b1100 !
b1100 (
1$
#493000
0$
#493500
b1101 !
b1101 (
1$
#494000
0$
#494500
b1110 !
b1110 (
1$
#495000
0$
#495500
b1111 !
b1111 (
1$
#496000
0$
#496500
b10000 !
b10000 (
1$
#497000
0$
#497500
b10001 !
b10001 (
1$
#498000
0$
#498500
b10010 !
b10010 (
1$
#499000
0$
#499500
b10011 !
b10011 (
1$
#500000
0$
#500500
b10100 !
b10100 (
1$
#501000
0$
#501500
b10101 !
b10101 (
1$
#502000
0$
#502500
b10110 !
b10110 (
1$
#503000
0$
#503500
b10111 !
b10111 (
1$
#504000
0$
#504500
b11000 !
b11000 (
1$
#505000
0$
#505500
b11001 !
b11001 (
1$
#506000
0$
#506500
b11010 !
b11010 (
1$
#507000
0$
#507500
b11011 !
b11011 (
1$
#508000
0$
#508500
b11100 !
b11100 (
1$
#509000
0$
#509500
b11101 !
b11101 (
1$
#510000
0$
#510500
b11110 !
b11110 (
1$
#511000
0$
#511500
b11111 !
b11111 (
1$
#512000
0$
#512500
b100000 !
b100000 (
1$
#513000
0$
#513500
b100001 !
b100001 (
1$
#514000
0$
#514500
b100010 !
b100010 (
1$
#515000
0$
#515500
b100011 !
b100011 (
1$
#516000
0$
#516500
b100100 !
b100100 (
1$
#517000
0$
#517500
b100101 !
b100101 (
1$
#518000
0$
#518500
b100110 !
b100110 (
1$
#519000
0$
#519500
b100111 !
b100111 (
1$
#520000
0$
#520500
b101000 !
b101000 (
1$
#521000
0$
#521500
b101001 !
b101001 (
1$
#522000
0$
#522500
b101010 !
b101010 (
1$
#523000
0$
#523500
b101011 !
b101011 (
1$
#524000
0$
