combinational/decoder/decoder3_8.v
module decoder3_8(
    input logic [2:0] a_in,
    output logic [7:0] a_out
);
always @(a_in) begin
    a_out = 8'b00000001<<a_in;
end

endmodule

combinational/decoder/decoder3_8_tb.v
module decoder3_8_tb;
  reg [2:0] a_in;
  wire [7:0] a_out;

  decoder3_8 uut(
    .a_in(a_in),
    .a_out(a_out)
  );
  initial begin
    a_in = 3'b000;
    $monitor("Time = %0t a_in = %b a_out =%b", $time, a_in, a_out);
    #10 a_in = 3'b001;
    #10 a_in = 3'b010;
    #10 a_in = 3'b011;
    #10 a_in = 3'b100;
    #10 a_in = 3'b101;
    #10 a_in = 3'b110;
    #10 a_in = 3'b111;

  end
  initial begin
    $dumpfile("decoder3_8.vcd");
    $dumpvars(0, decoder3_8_tb);
  end

endmodule

combinational/decoder/decoder3_8.vcd
$date
	Mon Sep 23 02:15:23 2024
$end
$version
	Icarus Verilog
$end
$timescale
	1s
$end
$scope module decoder3_8_tb $end
$var wire 8 ! a_out [7:0] $end
$var reg 3 " a_in [2:0] $end
$scope module uut $end
$var wire 3 # a_in [2:0] $end
$var reg 8 $ a_out [7:0] $end
$upscope $end
$upscope $end
$enddefinitions $end
#0
$dumpvars
b1 $
b0 #
b0 "
b1 !
$end
#10
b10 !
b10 $
b1 "
b1 #
#20
b100 !
b100 $
b10 "
b10 #
#30
b1000 !
b1000 $
b11 "
b11 #
#40
b10000 !
b10000 $
b100 "
b100 #
#50
b100000 !
b100000 $
b101 "
b101 #
#60
b1000000 !
b1000000 $
b110 "
b110 #
#70
b10000000 !
b10000000 $
b111 "
b111 #
