combinational/encoder/p_encoder7_3.v
module p_encoder7_3 (
    input logic [7:0] a_in,
    output logic [2:0] a_out    
);
  always @(a_in) begin
    casez (a_in)
        8'b1??????? : a_out = 3'b111;
        8'b01?????? : a_out = 3'b110;
        8'b001????? : a_out = 3'b101;
        8'b0001???? : a_out = 3'b100;
        8'b00001??? : a_out = 3'b011;
        8'b000001?? : a_out = 3'b010;
        8'b0000001? : a_out = 3'b001;
        default: a_out = 3'b000;
    endcase
  end      
endmodule

combinational/encoder/p_encoder7_3_tb.v
module p_encoder7_3_tb;
    reg [7:0] a_in;
    wire [2:0] a_out;

    p_encoder7_3 uut(
        .a_in(a_in),
        .a_out(a_out)
    );
    initial begin
        a_in = 8'h00;
        $monitor("Time = %0t a_in = %0h a_out = %0b", $time, a_in, a_out);
        #10 a_in = 8'h80;
        #10 a_in = 8'h43;
        #10 a_in = 8'h2F;
        #10 a_in = 8'h18;
        #10 a_in = 8'h08;
        #10 a_in = 8'h04;
        #10 a_in = 8'h02;
        #10 a_in = 8'h01;
    end

    initial begin
        $dumpfile("Priority_Encoder.vcd");
        $dumpvars(0, p_encoder7_3_tb);
    end
    
endmodule

combinational/encoder/Priority_Encoder.vcd
$date
	Mon Sep 23 23:19:26 2024
$end
$version
	Icarus Verilog
$end
$timescale
	1s
$end
$scope module p_encoder7_3_tb $end
$var wire 3 ! a_out [2:0] $end
$var reg 8 " a_in [7:0] $end
$scope module uut $end
$var wire 8 # a_in [7:0] $end
$var reg 3 $ a_out [2:0] $end
$upscope $end
$upscope $end
$enddefinitions $end
#0
$dumpvars
b0 $
b0 #
b0 "
b0 !
$end
#10
b111 !
b111 $
b10000000 "
b10000000 #
#20
b110 !
b110 $
b1000011 "
b1000011 #
#30
b101 !
b101 $
b101111 "
b101111 #
#40
b100 !
b100 $
b11000 "
b11000 #
#50
b11 !
b11 $
b1000 "
b1000 #
#60
b10 !
b10 $
b100 "
b100 #
#70
b1 !
b1 $
b10 "
b10 #
#80
b0 !
b0 $
b1 "
b1 #
