8bitalu/8bitalu_redone/ALU_8bit.v
module ALU_8bit (
  input [2:0] operation,
  input [7:0] operand_A,
  input [7:0] operand_B,
  output reg [15:0] result = 16'b0,
  output reg carry_flag = 1'b0,
  output reg zero_flag = 1'b0
);

parameter [2:0] ADD = 3'b000,
               SUB = 3'b001,
               MUL = 3'b010,
               AND = 3'b011,
               OR  = 3'b100,
               NAND = 3'b101,
               NOR  = 3'b110,
               XOR  = 3'b111;

always @ (operation or operand_A or operand_B)
begin
  case (operation)
    ADD: begin
      result = operand_A + operand_B;
      carry_flag = result[8];
      zero_flag = (result == 16'b0);
    end

    SUB: begin
      result = operand_A - operand_B;
      carry_flag = result[8];
      zero_flag = (result == 16'b0);
    end

    MUL: begin
      result = operand_A * operand_B;
      zero_flag = (result == 16'b0);
    end

    AND: begin
      result = operand_A & operand_B;
      zero_flag = (result == 16'b0);
    end

    OR: begin
      result = operand_A | operand_B;
      zero_flag = (result == 16'b0);
    end

    NAND: begin
      result = ~(operand_A & operand_B);
      zero_flag = (result == 16'b0);
    end

    NOR: begin
      result = ~(operand_A | operand_B);
      zero_flag = (result == 16'b0);
    end

    XOR: begin
      result = operand_A ^ operand_B;
      zero_flag = (result == 16'b0);
    end

    default: begin
      result = 16'b0;
      carry_flag = 1'b0;
      zero_flag = 1'b0;
    end
  endcase
end

endmodule

8bitalu/8bitalu_redone/ALU_8bit_tb.v

module ALU_8bit_tb;

  // Inputs
  reg [2:0] operation;
  reg [7:0] operand_A;
  reg [7:0] operand_B;

  // Outputs
  wire [15:0] result;
  wire carry_flag;
  wire zero_flag;

  ALU_8bit dut (
    .operation(operation), .operand_A(operand_A), .operand_B(operand_B),
    .result(result), .carry_flag(carry_flag), .zero_flag(zero_flag) );

  reg clk = 0;
  always begin
    #5 clk = ~clk;
  end

  initial begin
    // Test ADD operation
    operation = 3'b000;
    operand_A = 8'b11011010;
    operand_B = 8'b00100111;
    #10;
    $display("ADD Result: %b, Carry: %b, Zero: %b", result, carry_flag, zero_flag);

    // Test SUB operation
    operation = 3'b001;
    operand_A = 8'b11011010;
    operand_B = 8'b00100111;
    #10;
    $display("SUB Result: %b, Carry: %b, Zero: %b", result, carry_flag, zero_flag);

    // Test MUL operation
    operation = 3'b010;
    operand_A = 8'b11011010;
    operand_B = 8'b00100111;
    #10;
    $display("MUL Result: %b, Zero: %b", result, zero_flag);

    // Test AND operation
    operation = 3'b011;
    operand_A = 8'b11011010;
    operand_B = 8'b00100111;
    #10;
    $display("AND Result: %b, Zero: %b", result, zero_flag);

    // Test OR operation
    operation = 3'b100;
    operand_A = 8'b11011010;
    operand_B = 8'b00100111;
    #10;
    $display("OR Result: %b, Zero: %b", result, zero_flag);

    // Test NAND operation
    operation = 3'b101;
    operand_A = 8'b11011010;
    operand_B = 8'b00100111;
    #10;
    $display("NAND Result: %b, Zero: %b", result, zero_flag);

    // Test NOR operation
    operation = 3'b110;
    operand_A = 8'b11011010;
    operand_B = 8'b00100111;
    #10;
    $display("NOR Result: %b, Zero: %b", result, zero_flag);

    // Test XOR operation
    operation = 3'b111;
    operand_A = 8'b11011010;
    operand_B = 8'b00100111;
    #10;
    $display("XOR Result: %b, Zero: %b", result, zero_flag);

    $finish;
  end
  initial begin
    $dumpfile("alu.vcd");
    $dumpvars(0, ALU_8bit_tb);
  end

endmodule

8bitalu/8bitalu_redone/alu.vcd
$date
	Sun Sep 29 13:45:28 2024
$end
$version
	Icarus Verilog
$end
$timescale
	1s
$end
$scope module ALU_8bit_tb $end
$var wire 1 ! zero_flag $end
$var wire 16 " result [15:0] $end
$var wire 1 # carry_flag $end
$var reg 1 $ clk $end
$var reg 8 % operand_A [7:0] $end
$var reg 8 & operand_B [7:0] $end
$var reg 3 ' operation [2:0] $end
$scope module dut $end
$var wire 8 ( operand_A [7:0] $end
$var wire 8 ) operand_B [7:0] $end
$var wire 3 * operation [2:0] $end
$var reg 1 # carry_flag $end
$var reg 16 + result [15:0] $end
$var reg 1 ! zero_flag $end
$upscope $end
$upscope $end
$enddefinitions $end
#0
$dumpvars
b100000001 +
b0 *
b100111 )
b11011010 (
b0 '
b100111 &
b11011010 %
0$
1#
b100000001 "
0!
$end
#5
1$
#10
0#
b10110011 "
b10110011 +
0$
b1 '
b1 *
#15
1$
#20
b10000100110110 "
b10000100110110 +
0$
b10 '
b10 *
#25
1$
#30
b10 "
b10 +
0$
b11 '
b11 *
#35
1$
#40
b11111111 "
b11111111 +
0$
b100 '
b100 *
#45
1$
#50
b1111111111111101 "
b1111111111111101 +
0$
b101 '
b101 *
#55
1$
#60
b1111111100000000 "
b1111111100000000 +
0$
b110 '
b110 *
#65
1$
#70
b11111101 "
b11111101 +
0$
b111 '
b111 *
